framewise_meet_client/__init__.py
framewise_meet_client/agent_connector.py
framewise_meet_client/app.py
framewise_meet_client/app_factory.py
framewise_meet_client/auth.py
framewise_meet_client/config.py
framewise_meet_client/connection.py
framewise_meet_client/constants.py
framewise_meet_client/error_handling.py
framewise_meet_client/errors.py
framewise_meet_client/event_handler.py
framewise_meet_client/exceptions.py
framewise_meet_client/interfaces.py
framewise_meet_client/logging_config.py
framewise_meet_client/messaging.py
framewise_meet_client/runner.py
framewise_meet_client/docs/architecture.md
framewise_meet_client/events/__init__.py
framewise_meet_client/events/base_handler.py
framewise_meet_client/events/connection_rejected_handler.py
framewise_meet_client/events/custom_ui_handler.py
framewise_meet_client/events/dispatcher.py
framewise_meet_client/events/exit_handler.py
framewise_meet_client/events/invoke_handler.py
framewise_meet_client/events/join_handler.py
framewise_meet_client/events/transcript_handler.py
framewise_meet_client/models/__init__.py
framewise_meet_client/models/inbound.py
framewise_meet_client/models/outbound.py
framewise_meet_client/runner/websocket_runner.py
framewise_meet_client-0.1.7.dist-info/METADATA
framewise_meet_client-0.1.7.dist-info/WHEEL
framewise_meet_client-0.1.7.dist-info/entry_points.txt
framewise_meet_client-0.1.7.dist-info/licenses/LICENSE
framewise_meet_client-0.1.7.dist-info/RECORD
