Metadata-Version: 2.4
Name: framewise-meet-client
Version: 0.1.7
Summary: Add your description here
Author-email: Sigireddy Balasai <sigireddybalasai@gmail.com>
License-File: LICENSE
Requires-Python: >=3.12
Requires-Dist: pydantic>=2.10.6
Requires-Dist: requests>=2.32.3
Requires-Dist: websockets>=13.1
